DSDL/Lab1/question1.v
module question1 (a,b,c,d,f);
  input a,b,c,d;
  output f;

  //level1
  and(ab1,a,b);
  and(ab2,a,b);
  
  //level2
  or(o1,ab1,c);
  or(o2,ab2,c);

  //level3
  not(n1,o1);

  //level4
  and(a3,n1,d);
  or(o3,o2,d);

  //level5
  and(f,a3,o3);

endmodule

DSDL/Lab1/question1_tb.v
`timescale 1ns/1ns
`include "question1.v"

module question1_tb();
  reg a,b,c,d;
  wire f;

  question1 q1(a,b,c,d,f);
  initial 
    begin 
      $dumpfile("question1_tb.vcd");
      $dumpvars(0,question1_tb);

      a=1'b0; b=1'b0; c=1'b0; d=1'b0;
      #20
      a=1'b0; b=1'b0; c=1'b0; d=1'b1;
      #20
      a=1'b0; b=1'b0; c=1'b1; d=1'b0;
      #20
      a=1'b0; b=1'b0; c=1'b1; d=1'b1;
      #20
      a=1'b0; b=1'b1; c=1'b0; d=1'b0;
      #20
      a=1'b0; b=1'b1; c=1'b0; d=1'b1;
      #20
      a=1'b0; b=1'b1; c=1'b1; d=1'b0;
      #20
      a=1'b0; b=1'b1; c=1'b1; d=1'b1;
      #20
      a=1'b1; b=1'b0; c=1'b0; d=1'b0;
      #20
      a=1'b1; b=1'b0; c=1'b0; d=1'b1;
      #20
      a=1'b1; b=1'b0; c=1'b1; d=1'b0;
      #20
      a=1'b1; b=1'b0; c=1'b1; d=1'b1;
      #20
      a=1'b1; b=1'b1; c=1'b0; d=1'b0;
      #20
      a=1'b1; b=1'b1; c=1'b0; d=1'b1;
      #20
      a=1'b1; b=1'b1; c=1'b1; d=1'b0;
      #20
      a=1'b1; b=1'b1; c=1'b1; d=1'b1;
      #20

      $display("Test Complete");
    end
endmodule

DSDL/Lab1/question1_tb.vcd
$date
	Mon Aug 29 05:23:53 2022
$end
$version
	Icarus Verilog
$end
$timescale
	1ns
$end
$scope module question1_tb $end
$var wire 1 ! f $end
$var reg 1 " a $end
$var reg 1 # b $end
$var reg 1 $ c $end
$var reg 1 % d $end
$scope module q1 $end
$var wire 1 " a $end
$var wire 1 & a3 $end
$var wire 1 ' ab1 $end
$var wire 1 ( ab2 $end
$var wire 1 # b $end
$var wire 1 $ c $end
$var wire 1 % d $end
$var wire 1 ! f $end
$var wire 1 ) n1 $end
$var wire 1 * o1 $end
$var wire 1 + o2 $end
$var wire 1 , o3 $end
$upscope $end
$upscope $end
$enddefinitions $end
#0
$dumpvars
0,
0+
0*
1)
0(
0'
0&
0%
0$
0#
0"
0!
$end
#20
1!
1&
1,
1%
#40
0!
0)
0&
1*
1+
0%
1$
#60
1%
#80
1)
0,
0*
0+
0%
0$
1#
#100
1!
1&
1,
1%
#120
0!
0)
0&
1*
1+
0%
1$
#140
1%
#160
1)
0,
0*
0+
0%
0$
0#
1"
#180
1!
1&
1,
1%
#200
0!
0)
0&
1*
1+
0%
1$
#220
1%
#240
1'
1(
0%
0$
1#
#260
1%
#280
0%
1$
#300
1%
