DSDL/Lab2/question2b.v
module question2b (a,b,c,d,f);

input a,b,c,d;
output f;

assign f = (~a | ~b | c) & (a | ~b | ~c) & (~a | b | ~d) & (~a | b | ~c);

endmodule

DSDL/Lab2/question2b_tb.v
`timescale 1ns/1ns
`include "question2b.v"

module question2b_tb();
  reg a,b,c,d;
  wire f;

  question2b q2b(a,b,c,d,f);
  initial
    begin
      $dumpfile("question2b_tb.vcd");
      $dumpvars(0,question2b_tb);

      a=1'b0; b=1'b0; c=1'b0; d=1'b0;
      #20
      a=1'b0; b=1'b0; c=1'b0; d=1'b1;
      #20
      a=1'b0; b=1'b0; c=1'b1; d=1'b0;
      #20
      a=1'b0; b=1'b0; c=1'b1; d=1'b1;
      #20
      a=1'b0; b=1'b1; c=1'b0; d=1'b0;
      #20
      a=1'b0; b=1'b1; c=1'b0; d=1'b1;
      #20
      a=1'b0; b=1'b1; c=1'b1; d=1'b0;
      #20
      a=1'b0; b=1'b1; c=1'b1; d=1'b1;
      #20
      a=1'b1; b=1'b0; c=1'b0; d=1'b0;
      #20
      a=1'b1; b=1'b0; c=1'b0; d=1'b1;
      #20
      a=1'b1; b=1'b0; c=1'b1; d=1'b0;
      #20
      a=1'b1; b=1'b0; c=1'b1; d=1'b1;
      #20
      a=1'b1; b=1'b1; c=1'b0; d=1'b0;
      #20
      a=1'b1; b=1'b1; c=1'b0; d=1'b1;
      #20
      a=1'b1; b=1'b1; c=1'b1; d=1'b0;
      #20
      a=1'b1; b=1'b1; c=1'b1; d=1'b1;
      #20

      $display ("Test complete");
    end
endmodule

DSDL/Lab2/question2b_tb.vcd
$date
	Thu Sep  1 16:13:25 2022
$end
$version
	Icarus Verilog
$end
$timescale
	1ns
$end
$scope module question2b_tb $end
$var wire 1 ! f $end
$var reg 1 " a $end
$var reg 1 # b $end
$var reg 1 $ c $end
$var reg 1 % d $end
$scope module q2b $end
$var wire 1 " a $end
$var wire 1 # b $end
$var wire 1 $ c $end
$var wire 1 % d $end
$var wire 1 ! f $end
$upscope $end
$upscope $end
$enddefinitions $end
#0
$dumpvars
0%
0$
0#
0"
1!
$end
#20
1%
#40
0%
1$
#60
1%
#80
0%
0$
1#
#100
1%
#120
0!
0%
1$
#140
1%
#160
1!
0%
0$
0#
1"
#180
0!
1%
#200
0%
1$
#220
1%
#240
0!
0%
0$
1#
#260
1%
#280
1!
0%
1$
#300
1%
