DSDL/lab3/question3.v
module question3(x1,x2,x3,x4,x5,f);

input x1,x2,x3,x4,x5;
output f;

assign g = x5 & (~x1 | x2);
assign f = g & (x3 ~^ x4) | ((~x3 & x4) & ~g);

endmodule

DSDL/Lab3/question3_tb.v
`timescale 1ns/1ns
`include "question3.v"

module question3_tb();
  reg x1,x2,x3,x4, x5;
  wire f;

  question3 q3(x1,x2,x3,x4,x5,f);
  initial
    begin
      $dumpfile("question3_tb.vcd");
      $dumpvars(0,question3_tb);

      x1=1'b0; x2=1'b0; x3=1'b0; x4=1'b0; x5=1'b1;
      #20
      x1=1'b0; x2=1'b0; x3=1'b0; x4=1'b1; x5=1'b0;
      #20
      x1=1'b0; x2=1'b0; x3=1'b1; x4=1'b1; x5=1'b1;
      #20
      x1=1'b0; x2=1'b1; x3=1'b0; x4=1'b0; x5=1'b1;
      #20
      x1=1'b0; x2=1'b1; x3=1'b0; x4=1'b1; x5=1'b0;
      #20
      x1=1'b1; x2=1'b0; x3=1'b0; x4=1'b1; x5=1'b0;
      #20
      x1=1'b1; x2=1'b0; x3=1'b0; x4=1'b1; x5=1'b1;
      #20
      x1=1'b1; x2=1'b1; x3=1'b0; x4=1'b0; x5=1'b1;
      #20
      x1=1'b1; x2=1'b1; x3=1'b1; x4=1'b1; x5=1'b1;
      #20
      x1=1'b0; x2=1'b0; x3=1'b0; x4=1'b1; x5=1'b1;
      #20
      x1=1'b0; x2=1'b0; x3=1'b1; x4=1'b0; x5=1'b1;
      #20
      x1=1'b1; x2=1'b0; x3=1'b1; x4=1'b0; x5=1'b0;
      #20

      $display("Test Complete");

      end
      endmodule

DSDL/Lab3/question3_tb.vcd
$date
	Thu Sep 15 15:29:25 2022
$end
$version
	Icarus Verilog
$end
$timescale
	1ns
$end
$scope module question3_tb $end
$var wire 1 ! f $end
$var reg 1 " x1 $end
$var reg 1 # x2 $end
$var reg 1 $ x3 $end
$var reg 1 % x4 $end
$var reg 1 & x5 $end
$scope module q3 $end
$var wire 1 ! f $end
$var wire 1 ' g $end
$var wire 1 " x1 $end
$var wire 1 # x2 $end
$var wire 1 $ x3 $end
$var wire 1 % x4 $end
$var wire 1 & x5 $end
$upscope $end
$upscope $end
$enddefinitions $end
#0
$dumpvars
1'
1&
0%
0$
0#
0"
1!
$end
#20
1!
0'
0&
1%
#40
1'
1&
1$
#60
0%
0$
1#
#80
1!
0'
0&
1%
#100
0#
1"
#120
1&
#140
1'
0%
1#
#160
1%
1$
#180
0!
0$
0#
0"
#200
0%
1$
#220
0'
0&
1"
