DSDL/Lab3/question1.v
module question1(a,b,c,d,f);

input a,b,c,d;
output f;

assign an = a ~& a;
assign cn = c ~& c;
assign f = ~((an ~& cn) & (an ~& d) & (b ~& cn) & (b ~& d));

endmodule

DSDL/Lab3/question1_tb.v
`timescale 1ns/1ns
`include "question1.v"

module question1_tb();
  reg a,b,c,d;
  wire f;

  question1 q1(a,b,c,d,f);
  initial
    begin
      $dumpfile("question1_tb.vcd");
      $dumpvars(0,question1_tb);

      a=1'b0; b=1'b0; c=1'b0; d=1'b0;
      #20
      a=1'b0; b=1'b0; c=1'b0; d=1'b1;
      #20
      a=1'b0; b=1'b0; c=1'b1; d=1'b0;
      #20
      a=1'b0; b=1'b0; c=1'b1; d=1'b1;
      #20
      a=1'b0; b=1'b1; c=1'b0; d=1'b0;
      #20
      a=1'b0; b=1'b1; c=1'b0; d=1'b1;
      #20
      a=1'b0; b=1'b1; c=1'b1; d=1'b0;
      #20
      a=1'b0; b=1'b1; c=1'b1; d=1'b1;
      #20
      a=1'b1; b=1'b0; c=1'b0; d=1'b0;
      #20
      a=1'b1; b=1'b0; c=1'b0; d=1'b1;
      #20
      a=1'b1; b=1'b0; c=1'b1; d=1'b0;
      #20
      a=1'b1; b=1'b0; c=1'b1; d=1'b1;
      #20
      a=1'b1; b=1'b1; c=1'b0; d=1'b0;
      #20
      a=1'b1; b=1'b1; c=1'b0; d=1'b1;
      #20
      a=1'b1; b=1'b1; c=1'b1; d=1'b0;
      #20
      a=1'b1; b=1'b1; c=1'b1; d=1'b1;
      #20

      $display ("Test complete");
    end
endmodule

DSDL/lab3/question1_tb.vcd
$date
	Thu Sep  8 16:00:42 2022
$end
$version
	Icarus Verilog
$end
$timescale
	1ns
$end
$scope module question1_tb $end
$var wire 1 ! f $end
$var reg 1 " a $end
$var reg 1 # b $end
$var reg 1 $ c $end
$var reg 1 % d $end
$scope module q1 $end
$var wire 1 " a $end
$var wire 1 & an $end
$var wire 1 # b $end
$var wire 1 $ c $end
$var wire 1 ' cn $end
$var wire 1 % d $end
$var wire 1 ! f $end
$upscope $end
$upscope $end
$enddefinitions $end
#0
$dumpvars
1'
1&
0%
0$
0#
0"
1!
$end
#20
1%
#40
0!
0'
0%
1$
#60
1!
1%
#80
1'
0%
0$
1#
#100
1%
#120
0!
0'
0%
1$
#140
1!
1%
#160
0!
1'
0&
0%
0$
0#
1"
#180
1%
#200
0'
0%
1$
#220
1%
#240
1!
1'
0%
0$
1#
#260
1%
#280
0!
0'
0%
1$
#300
1!
1%
