DSDL/Lab3/question2.v
module question2(a,b,c,d,f);

input a,b,c,d;
output f;

assign an = a ~| a;
assign bn = b ~| b;
assign cn = c ~| c;
assign dn = d ~| d;

assign f = ~((an ~| bn) | (cn ~| dn) | (bn ~| d));

endmodule

DSDL/Lab3/question2_tb.v
`timescale 1ns/1ns
`include "question2.v"

module question2_tb();
  reg a,b,c,d;
  wire f;

  question2 q2(a,b,c,d,f);
  initial
    begin
      $dumpfile("question2_tb.vcd");
      $dumpvars(0,question2_tb);

      a=1'b0; b=1'b0; c=1'b0; d=1'b0;
      #20
      a=1'b0; b=1'b0; c=1'b0; d=1'b1;
      #20
      a=1'b0; b=1'b0; c=1'b1; d=1'b0;
      #20
      a=1'b0; b=1'b0; c=1'b1; d=1'b1;
      #20
      a=1'b0; b=1'b1; c=1'b0; d=1'b0;
      #20
      a=1'b0; b=1'b1; c=1'b0; d=1'b1;
      #20
      a=1'b0; b=1'b1; c=1'b1; d=1'b0;
      #20
      a=1'b0; b=1'b1; c=1'b1; d=1'b1;
      #20
      a=1'b1; b=1'b0; c=1'b0; d=1'b0;
      #20
      a=1'b1; b=1'b0; c=1'b0; d=1'b1;
      #20
      a=1'b1; b=1'b0; c=1'b1; d=1'b0;
      #20
      a=1'b1; b=1'b0; c=1'b1; d=1'b1;
      #20
      a=1'b1; b=1'b1; c=1'b0; d=1'b0;
      #20
      a=1'b1; b=1'b1; c=1'b0; d=1'b1;
      #20
      a=1'b1; b=1'b1; c=1'b1; d=1'b0;
      #20
      a=1'b1; b=1'b1; c=1'b1; d=1'b1;
      #20

      $display ("Test complete");
    end
endmodule

DSDL/Lab3/question2_tb.vcd
$date
	Thu Sep  8 16:08:24 2022
$end
$version
	Icarus Verilog
$end
$timescale
	1ns
$end
$scope module question2_tb $end
$var wire 1 ! f $end
$var reg 1 " a $end
$var reg 1 # b $end
$var reg 1 $ c $end
$var reg 1 % d $end
$scope module q2 $end
$var wire 1 " a $end
$var wire 1 & an $end
$var wire 1 # b $end
$var wire 1 ' bn $end
$var wire 1 $ c $end
$var wire 1 ( cn $end
$var wire 1 % d $end
$var wire 1 ) dn $end
$var wire 1 ! f $end
$upscope $end
$upscope $end
$enddefinitions $end
#0
$dumpvars
1)
1(
1'
1&
0%
0$
0#
0"
1!
$end
#20
0)
1%
#40
1)
0(
0%
1$
#60
0!
0)
1%
#80
1)
1(
0'
0%
0$
1#
#100
1!
0)
1%
#120
0!
1)
0(
0%
1$
#140
0!
0)
1%
#160
1!
1)
1(
1'
0&
0%
0$
0#
1"
#180
0)
1%
#200
1)
0(
0%
1$
#220
0!
0)
1%
#240
1)
1(
0'
0%
0$
1#
#260
0)
1%
#280
1)
0(
0%
1$
#300
0)
1%
